lexikos/__init__.py
lexikos/g2p.py
lexikos/lexicon.py
lexikos/normalizer.py
lexikos/t5.py
lexikos/utils.py
lexikos/dict/asr-data/austalk_en_au.tsv
lexikos/dict/asr-data/sc_cw_en_au.tsv
lexikos/dict/cmudict-ipa/cmudict-0.7b-ipa-segmented.tsv
lexikos/dict/cmudict-ipa/librispeech-lexicon-200k-allothers-g2p-ipa.tsv
lexikos/dict/synthetic/bookbot_en_v1-v2_lexicon.tsv
lexikos/dict/synthetic/bookbot_en_v1-v2_lexicon_zipformer.tsv
lexikos/dict/synthetic/common-voice-accent-au_lexicon.tsv
lexikos/dict/synthetic/common-voice-accent-ca_lexicon.tsv
lexikos/dict/synthetic/common-voice-accent-gb_lexicon.tsv
lexikos/dict/synthetic/common-voice-accent-id_lexicon.tsv
lexikos/dict/synthetic/common-voice-accent-in_lexicon.tsv
lexikos/dict/synthetic/common-voice-accent-nz_lexicon.tsv
lexikos/dict/synthetic/common-voice-accent-us_lexicon.tsv
lexikos/dict/synthetic/l2-arctic-en-cn_lexicon.tsv
lexikos/dict/synthetic/l2-arctic-en-eg_lexicon.tsv
lexikos/dict/synthetic/l2-arctic-en-es_lexicon.tsv
lexikos/dict/synthetic/l2-arctic-en-in_lexicon.tsv
lexikos/dict/synthetic/l2-arctic-en-kr_lexicon.tsv
lexikos/dict/synthetic/l2-arctic-en-vn_lexicon.tsv
lexikos/dict/synthetic/librispeech-lexicon-en-id.tsv
lexikos/dict/synthetic/wu_lexicon.tsv
lexikos/dict/wikipron/eng_latn.tsv
lexikos/dict/wikipron/eng_latn_au_broad.tsv
lexikos/dict/wikipron/eng_latn_au_narrow.tsv
lexikos/dict/wikipron/eng_latn_ca_broad.tsv
lexikos/dict/wikipron/eng_latn_ca_narrow.tsv
lexikos/dict/wikipron/eng_latn_in_broad.tsv
lexikos/dict/wikipron/eng_latn_in_narrow.tsv
lexikos/dict/wikipron/eng_latn_nz_broad.tsv
lexikos/dict/wikipron/eng_latn_nz_narrow.tsv
lexikos/dict/wikipron/eng_latn_uk_broad.tsv
lexikos/dict/wikipron/eng_latn_uk_narrow.tsv
lexikos/dict/wikipron/eng_latn_us_broad.tsv
lexikos/dict/wikipron/eng_latn_us_narrow.tsv
lexikos-0.0.1rc7.dist-info/METADATA
lexikos-0.0.1rc7.dist-info/WHEEL
lexikos-0.0.1rc7.dist-info/top_level.txt
lexikos-0.0.1rc7.dist-info/RECORD
