Metadata-Version: 2.1
Name: lexikos
Version: 0.0.1rc7
Summary: A collection of pronunciation dictionaries and neural grapheme-to-phoneme models.
Home-page: https://github.com/bookbot-hive/lexikos
Author: w11wo
Author-email: w11wo <wilson@bookbotkids.com>, anantoj <gg.ananto@gmail.com>, DavidSamuell <davidsamuel.7878@gmail.com>
License: Apache License
Project-URL: Homepage, https://github.com/bookbot-hive/lexikos
Project-URL: Bug Tracker, https://github.com/bookbot-hive/lexikos/issues
Keywords: linguistics,pronunciation-dictionary,g2p,grapheme-to-phoneme,neural-g2p
Platform: linux
Platform: unix
Platform: windows
Classifier: License :: OSI Approved :: Apache Software License
Classifier: Programming Language :: Python :: 3
